veildata/__init__.py
veildata/cli.py
veildata/compose.py
veildata/core.py
veildata/diagnostics.py
veildata/engine.py
veildata/revealers.py
veildata/transforms.py
veildata/maskers/__init__.py
veildata/maskers/ner_bert.py
veildata/maskers/ner_spacy.py
veildata/maskers/regex.py
veildata-0.1.1.dist-info/licenses/LICENSE
veildata-0.1.1.dist-info/licenses/NOTICE
veildata-0.1.1.dist-info/METADATA
veildata-0.1.1.dist-info/WHEEL
veildata-0.1.1.dist-info/entry_points.txt
veildata-0.1.1.dist-info/top_level.txt
veildata-0.1.1.dist-info/RECORD
