Metadata-Version: 2.4
Name: veildata
Version: 0.1.1
Summary: Framework for masking and unmasking PII.
Author: Eric
License: MIT
Keywords: veildata,pii,redaction,privacy,ai,nlp
Classifier: Programming Language :: Python :: 3
Classifier: License :: OSI Approved :: MIT License
Classifier: Operating System :: OS Independent
Requires-Python: >=3.9
License-File: LICENSE
License-File: NOTICE
Requires-Dist: pre-commit
Requires-Dist: black
Requires-Dist: ruff
Requires-Dist: en-core-web-sm
Requires-Dist: typer
Requires-Dist: rich
Provides-Extra: spacy
Requires-Dist: spacy>=3.8.2; extra == "spacy"
Provides-Extra: bert
Requires-Dist: torch>=2.0.0; extra == "bert"
Requires-Dist: transformers>=4.30.0; extra == "bert"
Provides-Extra: all
Requires-Dist: spacy==3.8.2; extra == "all"
Requires-Dist: torch>=2.0.0; extra == "all"
Requires-Dist: transformers>=4.30.0; extra == "all"
Requires-Dist: pytest>=8.3.5; extra == "all"
Dynamic: license-file
